[
  {
    "video": "P01/videos/P01_09_813.0_819.8",
    "answer_text": "turn-on",
    "direction": "forward",
    "triplet_id": "21112a6a",
    "noun_class": "46",
    "id": 4145
  },
  {
    "video": "P26/videos/P26_105_261.8_263.2",
    "answer_text": "turn-on",
    "direction": "forward",
    "triplet_id": "21112a6a",
    "noun_class": "46",
    "id": 4146
  },
  {
    "video": "P06/videos/P06_101_1223.2_1248.5",
    "answer_text": "turn-on",
    "direction": "forward",
    "triplet_id": "21112a6a",
    "noun_class": "46",
    "id": 4147
  },
  {
    "video": "P02/videos/P02_120_729.8_731.7",
    "answer_text": "turn-on",
    "direction": "forward",
    "triplet_id": "21112a6a",
    "noun_class": "46",
    "id": 4148
  },
  {
    "video": "P06/videos/P06_05_1011.7_1014.2",
    "answer_text": "turn-on",
    "direction": "forward",
    "triplet_id": "21112a6a",
    "noun_class": "46",
    "id": 4149
  },
  {
    "video": "P13/videos/P13_09_141.3_145.9",
    "answer_text": "turn-on",
    "direction": "forward",
    "triplet_id": "21112a6a",
    "noun_class": "46",
    "id": 4150
  },
  {
    "video": "P04/videos/P04_110_63.8_65.1",
    "answer_text": "turn-on",
    "direction": "forward",
    "triplet_id": "21112a6a",
    "noun_class": "46",
    "id": 4151
  },
  {
    "video": "P04/videos/P04_113_0.0_3.5",
    "answer_text": "turn-on",
    "direction": "forward",
    "triplet_id": "21112a6a",
    "noun_class": "46",
    "id": 4152
  },
  {
    "video": "P16/videos/P16_01_17.3_20.2",
    "answer_text": "turn-on",
    "direction": "forward",
    "triplet_id": "21112a6a",
    "noun_class": "46",
    "id": 4153
  },
  {
    "video": "P26/videos/P26_104_37.6_39.2",
    "answer_text": "turn-on",
    "direction": "forward",
    "triplet_id": "21112a6a",
    "noun_class": "46",
    "id": 4154
  },
  {
    "video": "P30/videos/P30_111_618.4_620.3",
    "answer_text": "turn-on",
    "direction": "forward",
    "triplet_id": "21112a6a",
    "noun_class": "46",
    "id": 4155
  },
  {
    "video": "P11/videos/P11_15_64.9_68.8",
    "answer_text": "turn-on",
    "direction": "forward",
    "triplet_id": "21112a6a",
    "noun_class": "46",
    "id": 4156
  },
  {
    "video": "P13/videos/P13_08_1028.1_1032.4",
    "answer_text": "turn-on",
    "direction": "forward",
    "triplet_id": "21112a6a",
    "noun_class": "46",
    "id": 4157
  },
  {
    "video": "P26/videos/P26_115_18.7_20.6",
    "answer_text": "turn-on",
    "direction": "forward",
    "triplet_id": "21112a6a",
    "noun_class": "46",
    "id": 4158
  },
  {
    "video": "P07/videos/P07_101_162.8_170.6",
    "answer_text": "turn-on",
    "direction": "forward",
    "triplet_id": "21112a6a",
    "noun_class": "46",
    "id": 4159
  },
  {
    "video": "P02/videos/P02_112_1023.5_1029.0",
    "answer_text": "turn-on",
    "direction": "forward",
    "triplet_id": "21112a6a",
    "noun_class": "46",
    "id": 4160
  },
  {
    "video": "P26/videos/P26_04_42.1_43.9",
    "answer_text": "turn-on",
    "direction": "forward",
    "triplet_id": "21112a6a",
    "noun_class": "46",
    "id": 4161
  },
  {
    "video": "P24/videos/P24_08_230.5_235.1",
    "answer_text": "turn-on",
    "direction": "forward",
    "triplet_id": "21112a6a",
    "noun_class": "46",
    "id": 4162
  },
  {
    "video": "P35/videos/P35_103_1386.3_1390.6",
    "answer_text": "turn-on",
    "direction": "forward",
    "triplet_id": "21112a6a",
    "noun_class": "46",
    "id": 4163
  },
  {
    "video": "P28/videos/P28_106_19.1_21.6",
    "answer_text": "turn-on",
    "direction": "forward",
    "triplet_id": "21112a6a",
    "noun_class": "46",
    "id": 4164
  },
  {
    "video": "P06/videos/P06_108_33.5_40.7",
    "answer_text": "turn-on",
    "direction": "forward",
    "triplet_id": "21112a6a",
    "noun_class": "46",
    "id": 4165
  },
  {
    "video": "P22/videos/P22_16_902.1_903.6",
    "answer_text": "turn-on",
    "direction": "forward",
    "triplet_id": "21112a6a",
    "noun_class": "46",
    "id": 4166
  },
  {
    "video": "P26/videos/P26_119_3.0_4.8",
    "answer_text": "turn-on",
    "direction": "forward",
    "triplet_id": "21112a6a",
    "noun_class": "46",
    "id": 4167
  },
  {
    "video": "P15/videos/P15_02_219.1_228.9",
    "answer_text": "turn-on",
    "direction": "forward",
    "triplet_id": "21112a6a",
    "noun_class": "46",
    "id": 4168
  },
  {
    "video": "P03/videos/P03_119_13.0_14.5",
    "answer_text": "turn-on",
    "direction": "forward",
    "triplet_id": "21112a6a",
    "noun_class": "46",
    "id": 4169
  },
  {
    "video": "P11/videos/P11_105_13.0_22.4",
    "answer_text": "turn-on",
    "direction": "forward",
    "triplet_id": "21112a6a",
    "noun_class": "46",
    "id": 4170
  },
  {
    "video": "P03/videos/P03_122_14.8_19.2",
    "answer_text": "turn-on",
    "direction": "forward",
    "triplet_id": "21112a6a",
    "noun_class": "46",
    "id": 4171
  },
  {
    "video": "P28/videos/P28_10_3.0_5.3",
    "answer_text": "turn-on",
    "direction": "forward",
    "triplet_id": "21112a6a",
    "noun_class": "46",
    "id": 4172
  },
  {
    "video": "P11/videos/P11_05_10.0_11.5",
    "answer_text": "turn-on",
    "direction": "forward",
    "triplet_id": "21112a6a",
    "noun_class": "46",
    "id": 4173
  },
  {
    "video": "P11/videos/P11_103_4.1_6.0",
    "answer_text": "turn-on",
    "direction": "forward",
    "triplet_id": "21112a6a",
    "noun_class": "46",
    "id": 4174
  },
  {
    "video": "P13/videos/P13_08_2156.6_2158.5",
    "answer_text": "turn-off",
    "direction": "reverse",
    "triplet_id": "21112a6a",
    "noun_class": "46",
    "id": 4175
  },
  {
    "video": "P12/videos/P12_06_9.4_12.1",
    "answer_text": "turn-off",
    "direction": "reverse",
    "triplet_id": "21112a6a",
    "noun_class": "46",
    "id": 4176
  },
  {
    "video": "P07/videos/P07_103_26.5_27.8",
    "answer_text": "turn-off",
    "direction": "reverse",
    "triplet_id": "21112a6a",
    "noun_class": "46",
    "id": 4177
  },
  {
    "video": "P07/videos/P07_103_24.1_26.5",
    "answer_text": "turn-off",
    "direction": "reverse",
    "triplet_id": "21112a6a",
    "noun_class": "46",
    "id": 4178
  },
  {
    "video": "P11/videos/P11_104_4.4_5.9",
    "answer_text": "turn-off",
    "direction": "reverse",
    "triplet_id": "21112a6a",
    "noun_class": "46",
    "id": 4179
  },
  {
    "video": "P06/videos/P06_105_81.4_89.0",
    "answer_text": "turn-off",
    "direction": "reverse",
    "triplet_id": "21112a6a",
    "noun_class": "46",
    "id": 4180
  },
  {
    "video": "P04/videos/P04_109_750.0_752.2",
    "answer_text": "turn-off",
    "direction": "reverse",
    "triplet_id": "21112a6a",
    "noun_class": "46",
    "id": 4181
  },
  {
    "video": "P22/videos/P22_14_557.9_559.4",
    "answer_text": "turn-off",
    "direction": "reverse",
    "triplet_id": "21112a6a",
    "noun_class": "46",
    "id": 4182
  },
  {
    "video": "P24/videos/P24_05_1434.9_1436.8",
    "answer_text": "turn-off",
    "direction": "reverse",
    "triplet_id": "21112a6a",
    "noun_class": "46",
    "id": 4183
  },
  {
    "video": "P13/videos/P13_07_29.0_30.9",
    "answer_text": "turn-off",
    "direction": "reverse",
    "triplet_id": "21112a6a",
    "noun_class": "46",
    "id": 4184
  },
  {
    "video": "P22/videos/P22_08_863.2_864.8",
    "answer_text": "turn-off",
    "direction": "reverse",
    "triplet_id": "21112a6a",
    "noun_class": "46",
    "id": 4185
  },
  {
    "video": "P24/videos/P24_01_679.5_688.0",
    "answer_text": "turn-off",
    "direction": "reverse",
    "triplet_id": "21112a6a",
    "noun_class": "46",
    "id": 4186
  },
  {
    "video": "P12/videos/P12_05_13.9_17.0",
    "answer_text": "turn-off",
    "direction": "reverse",
    "triplet_id": "21112a6a",
    "noun_class": "46",
    "id": 4187
  },
  {
    "video": "P26/videos/P26_117_6.2_8.1",
    "answer_text": "turn-off",
    "direction": "reverse",
    "triplet_id": "21112a6a",
    "noun_class": "46",
    "id": 4188
  },
  {
    "video": "P22/videos/P22_07_2161.8_2164.6",
    "answer_text": "turn-off",
    "direction": "reverse",
    "triplet_id": "21112a6a",
    "noun_class": "46",
    "id": 4189
  },
  {
    "video": "P16/videos/P16_01_705.5_707.4",
    "answer_text": "turn-off",
    "direction": "reverse",
    "triplet_id": "21112a6a",
    "noun_class": "46",
    "id": 4190
  },
  {
    "video": "P03/videos/P03_120_403.5_404.2",
    "answer_text": "turn-off",
    "direction": "reverse",
    "triplet_id": "21112a6a",
    "noun_class": "46",
    "id": 4191
  },
  {
    "video": "P28/videos/P28_14_2.7_5.2",
    "answer_text": "turn-off",
    "direction": "reverse",
    "triplet_id": "21112a6a",
    "noun_class": "46",
    "id": 4192
  },
  {
    "video": "P04/videos/P04_116_230.4_231.0",
    "answer_text": "turn-off",
    "direction": "reverse",
    "triplet_id": "21112a6a",
    "noun_class": "46",
    "id": 4193
  },
  {
    "video": "P03/videos/P03_123_68.1_69.1",
    "answer_text": "turn-off",
    "direction": "reverse",
    "triplet_id": "21112a6a",
    "noun_class": "46",
    "id": 4194
  },
  {
    "video": "P14/videos/P14_02_20.3_23.1",
    "answer_text": "turn-off",
    "direction": "reverse",
    "triplet_id": "21112a6a",
    "noun_class": "46",
    "id": 4195
  },
  {
    "video": "P02/videos/P02_115_11.6_14.7",
    "answer_text": "turn-off",
    "direction": "reverse",
    "triplet_id": "21112a6a",
    "noun_class": "46",
    "id": 4196
  },
  {
    "video": "P22/videos/P22_07_1843.4_1845.6",
    "answer_text": "turn-off",
    "direction": "reverse",
    "triplet_id": "21112a6a",
    "noun_class": "46",
    "id": 4197
  },
  {
    "video": "P13/videos/P13_08_2202.6_2204.4",
    "answer_text": "turn-off",
    "direction": "reverse",
    "triplet_id": "21112a6a",
    "noun_class": "46",
    "id": 4198
  },
  {
    "video": "P06/videos/P06_110_11.4_18.0",
    "answer_text": "turn-off",
    "direction": "reverse",
    "triplet_id": "21112a6a",
    "noun_class": "46",
    "id": 4199
  },
  {
    "video": "P01/videos/P01_10_3.1_7.5",
    "answer_text": "turn-off",
    "direction": "reverse",
    "triplet_id": "21112a6a",
    "noun_class": "46",
    "id": 4200
  },
  {
    "video": "P30/videos/P30_112_4.5_6.8",
    "answer_text": "turn-off",
    "direction": "reverse",
    "triplet_id": "21112a6a",
    "noun_class": "46",
    "id": 4201
  }
]