[
  {
    "video": "P22_07_166.mp4",
    "answer_text": "pick-up",
    "direction": "forward",
    "triplet_id": "745e4b78",
    "noun_class": "31",
    "id": 8003
  },
  {
    "video": "P02_03_236.mp4",
    "answer_text": "pick-up",
    "direction": "forward",
    "triplet_id": "745e4b78",
    "noun_class": "31",
    "id": 8004
  },
  {
    "video": "P06_09_139.mp4",
    "answer_text": "pick-up",
    "direction": "forward",
    "triplet_id": "745e4b78",
    "noun_class": "31",
    "id": 8005
  },
  {
    "video": "P04_05_179.mp4",
    "answer_text": "pick-up",
    "direction": "forward",
    "triplet_id": "745e4b78",
    "noun_class": "31",
    "id": 8006
  },
  {
    "video": "P22_111_362.mp4",
    "answer_text": "pick-up",
    "direction": "forward",
    "triplet_id": "745e4b78",
    "noun_class": "31",
    "id": 8007
  },
  {
    "video": "P22_16_509.mp4",
    "answer_text": "pick-up",
    "direction": "forward",
    "triplet_id": "745e4b78",
    "noun_class": "31",
    "id": 8008
  },
  {
    "video": "P26_116_3.mp4",
    "answer_text": "pick-up",
    "direction": "forward",
    "triplet_id": "745e4b78",
    "noun_class": "31",
    "id": 8009
  },
  {
    "video": "P04_01_228.mp4",
    "answer_text": "pick-up",
    "direction": "forward",
    "triplet_id": "745e4b78",
    "noun_class": "31",
    "id": 8010
  },
  {
    "video": "P04_109_315.mp4",
    "answer_text": "pick-up",
    "direction": "forward",
    "triplet_id": "745e4b78",
    "noun_class": "31",
    "id": 8011
  },
  {
    "video": "P02_09_78.mp4",
    "answer_text": "pick-up",
    "direction": "forward",
    "triplet_id": "745e4b78",
    "noun_class": "31",
    "id": 8012
  },
  {
    "video": "P29_01_30.mp4",
    "answer_text": "pick-up",
    "direction": "forward",
    "triplet_id": "745e4b78",
    "noun_class": "31",
    "id": 8013
  },
  {
    "video": "P30_111_74.mp4",
    "answer_text": "pick-up",
    "direction": "forward",
    "triplet_id": "745e4b78",
    "noun_class": "31",
    "id": 8014
  },
  {
    "video": "P01_109_168.mp4",
    "answer_text": "pick-up",
    "direction": "forward",
    "triplet_id": "745e4b78",
    "noun_class": "31",
    "id": 8015
  },
  {
    "video": "P20_04_237.mp4",
    "answer_text": "pick-up",
    "direction": "forward",
    "triplet_id": "745e4b78",
    "noun_class": "31",
    "id": 8016
  },
  {
    "video": "P22_111_403.mp4",
    "answer_text": "pick-up",
    "direction": "forward",
    "triplet_id": "745e4b78",
    "noun_class": "31",
    "id": 8017
  },
  {
    "video": "P25_101_7.mp4",
    "answer_text": "pick-up",
    "direction": "forward",
    "triplet_id": "745e4b78",
    "noun_class": "31",
    "id": 8018
  },
  {
    "video": "P15_02_29.mp4",
    "answer_text": "pick-up",
    "direction": "forward",
    "triplet_id": "745e4b78",
    "noun_class": "31",
    "id": 8019
  },
  {
    "video": "P26_02_2.mp4",
    "answer_text": "pick-up",
    "direction": "forward",
    "triplet_id": "745e4b78",
    "noun_class": "31",
    "id": 8020
  },
  {
    "video": "P06_101_339.mp4",
    "answer_text": "pick-up",
    "direction": "forward",
    "triplet_id": "745e4b78",
    "noun_class": "31",
    "id": 8021
  },
  {
    "video": "P22_104_138.mp4",
    "answer_text": "pick-up",
    "direction": "forward",
    "triplet_id": "745e4b78",
    "noun_class": "31",
    "id": 8022
  },
  {
    "video": "P02_102_61.mp4",
    "answer_text": "pick-up",
    "direction": "forward",
    "triplet_id": "745e4b78",
    "noun_class": "31",
    "id": 8023
  },
  {
    "video": "P20_04_260.mp4",
    "answer_text": "pick-up",
    "direction": "forward",
    "triplet_id": "745e4b78",
    "noun_class": "31",
    "id": 8024
  },
  {
    "video": "P04_05_113.mp4",
    "answer_text": "pick-up",
    "direction": "forward",
    "triplet_id": "745e4b78",
    "noun_class": "31",
    "id": 8025
  },
  {
    "video": "P25_104_56.mp4",
    "answer_text": "pick-up",
    "direction": "forward",
    "triplet_id": "745e4b78",
    "noun_class": "31",
    "id": 8026
  },
  {
    "video": "P22_111_419.mp4",
    "answer_text": "pick-up",
    "direction": "forward",
    "triplet_id": "745e4b78",
    "noun_class": "31",
    "id": 8027
  },
  {
    "video": "P06_03_83.mp4",
    "answer_text": "pick-up",
    "direction": "forward",
    "triplet_id": "745e4b78",
    "noun_class": "31",
    "id": 8028
  },
  {
    "video": "P02_06_318.mp4",
    "answer_text": "pick-up",
    "direction": "forward",
    "triplet_id": "745e4b78",
    "noun_class": "31",
    "id": 8029
  },
  {
    "video": "P30_109_185.mp4",
    "answer_text": "pick-up",
    "direction": "forward",
    "triplet_id": "745e4b78",
    "noun_class": "31",
    "id": 8030
  },
  {
    "video": "P04_107_121.mp4",
    "answer_text": "pick-up",
    "direction": "forward",
    "triplet_id": "745e4b78",
    "noun_class": "31",
    "id": 8031
  },
  {
    "video": "P04_05_19.mp4",
    "answer_text": "pick-up",
    "direction": "forward",
    "triplet_id": "745e4b78",
    "noun_class": "31",
    "id": 8032
  },
  {
    "video": "P06_101_55.mp4",
    "answer_text": "pick-up",
    "direction": "forward",
    "triplet_id": "745e4b78",
    "noun_class": "31",
    "id": 8033
  },
  {
    "video": "P11_104_143.mp4",
    "answer_text": "pick-up",
    "direction": "forward",
    "triplet_id": "745e4b78",
    "noun_class": "31",
    "id": 8034
  },
  {
    "video": "P11_16_80.mp4",
    "answer_text": "pick-up",
    "direction": "forward",
    "triplet_id": "745e4b78",
    "noun_class": "31",
    "id": 8035
  },
  {
    "video": "P11_104_58.mp4",
    "answer_text": "pick-up",
    "direction": "forward",
    "triplet_id": "745e4b78",
    "noun_class": "31",
    "id": 8036
  },
  {
    "video": "P02_102_62.mp4",
    "answer_text": "pick-up",
    "direction": "forward",
    "triplet_id": "745e4b78",
    "noun_class": "31",
    "id": 8037
  },
  {
    "video": "P25_106_138.mp4",
    "answer_text": "pick-up",
    "direction": "forward",
    "triplet_id": "745e4b78",
    "noun_class": "31",
    "id": 8038
  },
  {
    "video": "P22_117_203.mp4",
    "answer_text": "pick-up",
    "direction": "forward",
    "triplet_id": "745e4b78",
    "noun_class": "31",
    "id": 8039
  },
  {
    "video": "P22_113_59.mp4",
    "answer_text": "pick-up",
    "direction": "forward",
    "triplet_id": "745e4b78",
    "noun_class": "31",
    "id": 8040
  },
  {
    "video": "P02_09_254.mp4",
    "answer_text": "pick-up",
    "direction": "forward",
    "triplet_id": "745e4b78",
    "noun_class": "31",
    "id": 8041
  },
  {
    "video": "P22_111_405.mp4",
    "answer_text": "pick-up",
    "direction": "forward",
    "triplet_id": "745e4b78",
    "noun_class": "31",
    "id": 8042
  },
  {
    "video": "P04_02_255.mp4",
    "answer_text": "pick-up",
    "direction": "forward",
    "triplet_id": "745e4b78",
    "noun_class": "31",
    "id": 8043
  },
  {
    "video": "P25_09_32.mp4",
    "answer_text": "pick-up",
    "direction": "forward",
    "triplet_id": "745e4b78",
    "noun_class": "31",
    "id": 8044
  },
  {
    "video": "P30_111_240.mp4",
    "answer_text": "pick-up",
    "direction": "forward",
    "triplet_id": "745e4b78",
    "noun_class": "31",
    "id": 8045
  },
  {
    "video": "P13_08_64.mp4",
    "answer_text": "pick-up",
    "direction": "forward",
    "triplet_id": "745e4b78",
    "noun_class": "31",
    "id": 8046
  },
  {
    "video": "P02_09_124.mp4",
    "answer_text": "pick-up",
    "direction": "forward",
    "triplet_id": "745e4b78",
    "noun_class": "31",
    "id": 8047
  },
  {
    "video": "P26_119_23.mp4",
    "answer_text": "pick-up",
    "direction": "forward",
    "triplet_id": "745e4b78",
    "noun_class": "31",
    "id": 8048
  },
  {
    "video": "P30_111_423.mp4",
    "answer_text": "pick-up",
    "direction": "forward",
    "triplet_id": "745e4b78",
    "noun_class": "31",
    "id": 8049
  },
  {
    "video": "P25_104_5.mp4",
    "answer_text": "pick-up",
    "direction": "forward",
    "triplet_id": "745e4b78",
    "noun_class": "31",
    "id": 8050
  },
  {
    "video": "P04_02_17.mp4",
    "answer_text": "pick-up",
    "direction": "forward",
    "triplet_id": "745e4b78",
    "noun_class": "31",
    "id": 8051
  },
  {
    "video": "P25_10_20.mp4",
    "answer_text": "pick-up",
    "direction": "forward",
    "triplet_id": "745e4b78",
    "noun_class": "31",
    "id": 8052
  },
  {
    "video": "P12_101_181.mp4",
    "answer_text": "pick-up",
    "direction": "forward",
    "triplet_id": "745e4b78",
    "noun_class": "31",
    "id": 8053
  },
  {
    "video": "P04_05_80.mp4",
    "answer_text": "pick-up",
    "direction": "forward",
    "triplet_id": "745e4b78",
    "noun_class": "31",
    "id": 8054
  },
  {
    "video": "P04_03_53.mp4",
    "answer_text": "pick-up",
    "direction": "forward",
    "triplet_id": "745e4b78",
    "noun_class": "31",
    "id": 8055
  },
  {
    "video": "P22_111_422.mp4",
    "answer_text": "pick-up",
    "direction": "forward",
    "triplet_id": "745e4b78",
    "noun_class": "31",
    "id": 8056
  },
  {
    "video": "P02_09_136.mp4",
    "answer_text": "pick-up",
    "direction": "forward",
    "triplet_id": "745e4b78",
    "noun_class": "31",
    "id": 8057
  },
  {
    "video": "P12_101_56.mp4",
    "answer_text": "pick-up",
    "direction": "forward",
    "triplet_id": "745e4b78",
    "noun_class": "31",
    "id": 8058
  },
  {
    "video": "P25_101_102.mp4",
    "answer_text": "pick-up",
    "direction": "forward",
    "triplet_id": "745e4b78",
    "noun_class": "31",
    "id": 8059
  },
  {
    "video": "P35_105_275.mp4",
    "answer_text": "pick-up",
    "direction": "forward",
    "triplet_id": "745e4b78",
    "noun_class": "31",
    "id": 8060
  },
  {
    "video": "P29_01_103.mp4",
    "answer_text": "pick-up",
    "direction": "forward",
    "triplet_id": "745e4b78",
    "noun_class": "31",
    "id": 8061
  },
  {
    "video": "P22_111_397.mp4",
    "answer_text": "pick-up",
    "direction": "forward",
    "triplet_id": "745e4b78",
    "noun_class": "31",
    "id": 8062
  },
  {
    "video": "P22_111_344.mp4",
    "answer_text": "pick-up",
    "direction": "forward",
    "triplet_id": "745e4b78",
    "noun_class": "31",
    "id": 8063
  },
  {
    "video": "P29_01_329.mp4",
    "answer_text": "pick-up",
    "direction": "forward",
    "triplet_id": "745e4b78",
    "noun_class": "31",
    "id": 8064
  },
  {
    "video": "P22_111_59.mp4",
    "answer_text": "pick-up",
    "direction": "forward",
    "triplet_id": "745e4b78",
    "noun_class": "31",
    "id": 8065
  },
  {
    "video": "P04_110_52.mp4",
    "answer_text": "pick-up",
    "direction": "forward",
    "triplet_id": "745e4b78",
    "noun_class": "31",
    "id": 8066
  },
  {
    "video": "P24_07_144.mp4",
    "answer_text": "pick-up",
    "direction": "forward",
    "triplet_id": "745e4b78",
    "noun_class": "31",
    "id": 8067
  },
  {
    "video": "P11_05_304.mp4",
    "answer_text": "pick-up",
    "direction": "forward",
    "triplet_id": "745e4b78",
    "noun_class": "31",
    "id": 8068
  },
  {
    "video": "P25_106_37.mp4",
    "answer_text": "pick-up",
    "direction": "forward",
    "triplet_id": "745e4b78",
    "noun_class": "31",
    "id": 8069
  },
  {
    "video": "P02_09_86.mp4",
    "answer_text": "pick-up",
    "direction": "forward",
    "triplet_id": "745e4b78",
    "noun_class": "31",
    "id": 8070
  },
  {
    "video": "P22_111_341.mp4",
    "answer_text": "pick-up",
    "direction": "forward",
    "triplet_id": "745e4b78",
    "noun_class": "31",
    "id": 8071
  },
  {
    "video": "P26_20_3.mp4",
    "answer_text": "pick-up",
    "direction": "forward",
    "triplet_id": "745e4b78",
    "noun_class": "31",
    "id": 8072
  },
  {
    "video": "P04_02_228.mp4",
    "answer_text": "pick-up",
    "direction": "forward",
    "triplet_id": "745e4b78",
    "noun_class": "31",
    "id": 8073
  },
  {
    "video": "P26_115_14.mp4",
    "answer_text": "pick-up",
    "direction": "forward",
    "triplet_id": "745e4b78",
    "noun_class": "31",
    "id": 8074
  },
  {
    "video": "P20_01_51.mp4",
    "answer_text": "pick-up",
    "direction": "forward",
    "triplet_id": "745e4b78",
    "noun_class": "31",
    "id": 8075
  },
  {
    "video": "P01_105_135.mp4",
    "answer_text": "pick-up",
    "direction": "forward",
    "triplet_id": "745e4b78",
    "noun_class": "31",
    "id": 8076
  },
  {
    "video": "P04_01_124.mp4",
    "answer_text": "pick-up",
    "direction": "forward",
    "triplet_id": "745e4b78",
    "noun_class": "31",
    "id": 8077
  },
  {
    "video": "P04_110_176.mp4",
    "answer_text": "pick-up",
    "direction": "forward",
    "triplet_id": "745e4b78",
    "noun_class": "31",
    "id": 8078
  },
  {
    "video": "P04_112_53.mp4",
    "answer_text": "pick-up",
    "direction": "forward",
    "triplet_id": "745e4b78",
    "noun_class": "31",
    "id": 8079
  },
  {
    "video": "P22_16_363.mp4",
    "answer_text": "pick-up",
    "direction": "forward",
    "triplet_id": "745e4b78",
    "noun_class": "31",
    "id": 8080
  },
  {
    "video": "P26_104_91.mp4",
    "answer_text": "pick-up",
    "direction": "forward",
    "triplet_id": "745e4b78",
    "noun_class": "31",
    "id": 8081
  },
  {
    "video": "P26_119_28.mp4",
    "answer_text": "put-down",
    "direction": "reverse",
    "triplet_id": "745e4b78",
    "noun_class": "31",
    "id": 8082
  },
  {
    "video": "P22_117_207.mp4",
    "answer_text": "put-down",
    "direction": "reverse",
    "triplet_id": "745e4b78",
    "noun_class": "31",
    "id": 8083
  },
  {
    "video": "P30_111_247.mp4",
    "answer_text": "put-down",
    "direction": "reverse",
    "triplet_id": "745e4b78",
    "noun_class": "31",
    "id": 8084
  },
  {
    "video": "P25_101_103.mp4",
    "answer_text": "put-down",
    "direction": "reverse",
    "triplet_id": "745e4b78",
    "noun_class": "31",
    "id": 8085
  },
  {
    "video": "P26_20_6.mp4",
    "answer_text": "put-down",
    "direction": "reverse",
    "triplet_id": "745e4b78",
    "noun_class": "31",
    "id": 8086
  },
  {
    "video": "P02_03_147.mp4",
    "answer_text": "put-down",
    "direction": "reverse",
    "triplet_id": "745e4b78",
    "noun_class": "31",
    "id": 8087
  },
  {
    "video": "P02_03_153.mp4",
    "answer_text": "put-down",
    "direction": "reverse",
    "triplet_id": "745e4b78",
    "noun_class": "31",
    "id": 8088
  },
  {
    "video": "P04_02_229.mp4",
    "answer_text": "put-down",
    "direction": "reverse",
    "triplet_id": "745e4b78",
    "noun_class": "31",
    "id": 8089
  },
  {
    "video": "P26_104_96.mp4",
    "answer_text": "put-down",
    "direction": "reverse",
    "triplet_id": "745e4b78",
    "noun_class": "31",
    "id": 8090
  },
  {
    "video": "P04_01_127.mp4",
    "answer_text": "put-down",
    "direction": "reverse",
    "triplet_id": "745e4b78",
    "noun_class": "31",
    "id": 8091
  },
  {
    "video": "P06_09_143.mp4",
    "answer_text": "put-down",
    "direction": "reverse",
    "triplet_id": "745e4b78",
    "noun_class": "31",
    "id": 8092
  },
  {
    "video": "P22_111_400.mp4",
    "answer_text": "put-down",
    "direction": "reverse",
    "triplet_id": "745e4b78",
    "noun_class": "31",
    "id": 8093
  },
  {
    "video": "P11_05_39.mp4",
    "answer_text": "put-down",
    "direction": "reverse",
    "triplet_id": "745e4b78",
    "noun_class": "31",
    "id": 8094
  },
  {
    "video": "P26_02_90.mp4",
    "answer_text": "put-down",
    "direction": "reverse",
    "triplet_id": "745e4b78",
    "noun_class": "31",
    "id": 8095
  },
  {
    "video": "P04_112_54.mp4",
    "answer_text": "put-down",
    "direction": "reverse",
    "triplet_id": "745e4b78",
    "noun_class": "31",
    "id": 8096
  },
  {
    "video": "P04_05_82.mp4",
    "answer_text": "put-down",
    "direction": "reverse",
    "triplet_id": "745e4b78",
    "noun_class": "31",
    "id": 8097
  },
  {
    "video": "P29_01_31.mp4",
    "answer_text": "put-down",
    "direction": "reverse",
    "triplet_id": "745e4b78",
    "noun_class": "31",
    "id": 8098
  },
  {
    "video": "P25_10_21.mp4",
    "answer_text": "put-down",
    "direction": "reverse",
    "triplet_id": "745e4b78",
    "noun_class": "31",
    "id": 8099
  },
  {
    "video": "P31_08_75.mp4",
    "answer_text": "put-down",
    "direction": "reverse",
    "triplet_id": "745e4b78",
    "noun_class": "31",
    "id": 8100
  },
  {
    "video": "P26_115_20.mp4",
    "answer_text": "put-down",
    "direction": "reverse",
    "triplet_id": "745e4b78",
    "noun_class": "31",
    "id": 8101
  },
  {
    "video": "P01_09_76.mp4",
    "answer_text": "put-down",
    "direction": "reverse",
    "triplet_id": "745e4b78",
    "noun_class": "31",
    "id": 8102
  },
  {
    "video": "P25_104_58.mp4",
    "answer_text": "put-down",
    "direction": "reverse",
    "triplet_id": "745e4b78",
    "noun_class": "31",
    "id": 8103
  },
  {
    "video": "P28_01_2.mp4",
    "answer_text": "put-down",
    "direction": "reverse",
    "triplet_id": "745e4b78",
    "noun_class": "31",
    "id": 8104
  },
  {
    "video": "P04_109_321.mp4",
    "answer_text": "put-down",
    "direction": "reverse",
    "triplet_id": "745e4b78",
    "noun_class": "31",
    "id": 8105
  },
  {
    "video": "P22_111_63.mp4",
    "answer_text": "put-down",
    "direction": "reverse",
    "triplet_id": "745e4b78",
    "noun_class": "31",
    "id": 8106
  },
  {
    "video": "P06_101_59.mp4",
    "answer_text": "put-down",
    "direction": "reverse",
    "triplet_id": "745e4b78",
    "noun_class": "31",
    "id": 8107
  },
  {
    "video": "P01_105_139.mp4",
    "answer_text": "put-down",
    "direction": "reverse",
    "triplet_id": "745e4b78",
    "noun_class": "31",
    "id": 8108
  },
  {
    "video": "P13_08_66.mp4",
    "answer_text": "put-down",
    "direction": "reverse",
    "triplet_id": "745e4b78",
    "noun_class": "31",
    "id": 8109
  },
  {
    "video": "P06_03_80.mp4",
    "answer_text": "put-down",
    "direction": "reverse",
    "triplet_id": "745e4b78",
    "noun_class": "31",
    "id": 8110
  },
  {
    "video": "P20_04_242.mp4",
    "answer_text": "put-down",
    "direction": "reverse",
    "triplet_id": "745e4b78",
    "noun_class": "31",
    "id": 8111
  },
  {
    "video": "P25_09_37.mp4",
    "answer_text": "put-down",
    "direction": "reverse",
    "triplet_id": "745e4b78",
    "noun_class": "31",
    "id": 8112
  },
  {
    "video": "P25_106_140.mp4",
    "answer_text": "put-down",
    "direction": "reverse",
    "triplet_id": "745e4b78",
    "noun_class": "31",
    "id": 8113
  },
  {
    "video": "P11_16_81.mp4",
    "answer_text": "put-down",
    "direction": "reverse",
    "triplet_id": "745e4b78",
    "noun_class": "31",
    "id": 8114
  },
  {
    "video": "P22_16_367.mp4",
    "answer_text": "put-down",
    "direction": "reverse",
    "triplet_id": "745e4b78",
    "noun_class": "31",
    "id": 8115
  },
  {
    "video": "P35_105_279.mp4",
    "answer_text": "put-down",
    "direction": "reverse",
    "triplet_id": "745e4b78",
    "noun_class": "31",
    "id": 8116
  },
  {
    "video": "P22_111_423.mp4",
    "answer_text": "put-down",
    "direction": "reverse",
    "triplet_id": "745e4b78",
    "noun_class": "31",
    "id": 8117
  },
  {
    "video": "P01_05_238.mp4",
    "answer_text": "put-down",
    "direction": "reverse",
    "triplet_id": "745e4b78",
    "noun_class": "31",
    "id": 8118
  },
  {
    "video": "P25_101_13.mp4",
    "answer_text": "put-down",
    "direction": "reverse",
    "triplet_id": "745e4b78",
    "noun_class": "31",
    "id": 8119
  },
  {
    "video": "P26_105_115.mp4",
    "answer_text": "put-down",
    "direction": "reverse",
    "triplet_id": "745e4b78",
    "noun_class": "31",
    "id": 8120
  },
  {
    "video": "P01_17_177.mp4",
    "answer_text": "put-down",
    "direction": "reverse",
    "triplet_id": "745e4b78",
    "noun_class": "31",
    "id": 8121
  },
  {
    "video": "P22_104_142.mp4",
    "answer_text": "put-down",
    "direction": "reverse",
    "triplet_id": "745e4b78",
    "noun_class": "31",
    "id": 8122
  },
  {
    "video": "P11_104_86.mp4",
    "answer_text": "put-down",
    "direction": "reverse",
    "triplet_id": "745e4b78",
    "noun_class": "31",
    "id": 8123
  },
  {
    "video": "P22_16_510.mp4",
    "answer_text": "put-down",
    "direction": "reverse",
    "triplet_id": "745e4b78",
    "noun_class": "31",
    "id": 8124
  },
  {
    "video": "P06_101_343.mp4",
    "answer_text": "put-down",
    "direction": "reverse",
    "triplet_id": "745e4b78",
    "noun_class": "31",
    "id": 8125
  },
  {
    "video": "P22_113_63.mp4",
    "answer_text": "put-down",
    "direction": "reverse",
    "triplet_id": "745e4b78",
    "noun_class": "31",
    "id": 8126
  },
  {
    "video": "P01_05_251.mp4",
    "answer_text": "put-down",
    "direction": "reverse",
    "triplet_id": "745e4b78",
    "noun_class": "31",
    "id": 8127
  },
  {
    "video": "P25_05_81.mp4",
    "answer_text": "put-down",
    "direction": "reverse",
    "triplet_id": "745e4b78",
    "noun_class": "31",
    "id": 8128
  },
  {
    "video": "P31_01_50.mp4",
    "answer_text": "put-down",
    "direction": "reverse",
    "triplet_id": "745e4b78",
    "noun_class": "31",
    "id": 8129
  },
  {
    "video": "P22_111_365.mp4",
    "answer_text": "put-down",
    "direction": "reverse",
    "triplet_id": "745e4b78",
    "noun_class": "31",
    "id": 8130
  },
  {
    "video": "P22_111_348.mp4",
    "answer_text": "put-down",
    "direction": "reverse",
    "triplet_id": "745e4b78",
    "noun_class": "31",
    "id": 8131
  },
  {
    "video": "P26_116_4.mp4",
    "answer_text": "put-down",
    "direction": "reverse",
    "triplet_id": "745e4b78",
    "noun_class": "31",
    "id": 8132
  },
  {
    "video": "P01_01_153.mp4",
    "answer_text": "put-down",
    "direction": "reverse",
    "triplet_id": "745e4b78",
    "noun_class": "31",
    "id": 8133
  },
  {
    "video": "P22_111_425.mp4",
    "answer_text": "put-down",
    "direction": "reverse",
    "triplet_id": "745e4b78",
    "noun_class": "31",
    "id": 8134
  },
  {
    "video": "P01_09_327.mp4",
    "answer_text": "put-down",
    "direction": "reverse",
    "triplet_id": "745e4b78",
    "noun_class": "31",
    "id": 8135
  },
  {
    "video": "P30_109_187.mp4",
    "answer_text": "put-down",
    "direction": "reverse",
    "triplet_id": "745e4b78",
    "noun_class": "31",
    "id": 8136
  },
  {
    "video": "P04_110_56.mp4",
    "answer_text": "put-down",
    "direction": "reverse",
    "triplet_id": "745e4b78",
    "noun_class": "31",
    "id": 8137
  },
  {
    "video": "P01_18_348.mp4",
    "answer_text": "put-down",
    "direction": "reverse",
    "triplet_id": "745e4b78",
    "noun_class": "31",
    "id": 8138
  },
  {
    "video": "P04_01_230.mp4",
    "answer_text": "put-down",
    "direction": "reverse",
    "triplet_id": "745e4b78",
    "noun_class": "31",
    "id": 8139
  },
  {
    "video": "P04_107_125.mp4",
    "answer_text": "put-down",
    "direction": "reverse",
    "triplet_id": "745e4b78",
    "noun_class": "31",
    "id": 8140
  },
  {
    "video": "P01_09_568.mp4",
    "answer_text": "put-down",
    "direction": "reverse",
    "triplet_id": "745e4b78",
    "noun_class": "31",
    "id": 8141
  },
  {
    "video": "P12_101_59.mp4",
    "answer_text": "put-down",
    "direction": "reverse",
    "triplet_id": "745e4b78",
    "noun_class": "31",
    "id": 8142
  },
  {
    "video": "P26_19_25.mp4",
    "answer_text": "put-down",
    "direction": "reverse",
    "triplet_id": "745e4b78",
    "noun_class": "31",
    "id": 8143
  },
  {
    "video": "P22_07_172.mp4",
    "answer_text": "put-down",
    "direction": "reverse",
    "triplet_id": "745e4b78",
    "noun_class": "31",
    "id": 8144
  },
  {
    "video": "P20_04_265.mp4",
    "answer_text": "put-down",
    "direction": "reverse",
    "triplet_id": "745e4b78",
    "noun_class": "31",
    "id": 8145
  },
  {
    "video": "P28_11_31.mp4",
    "answer_text": "put-down",
    "direction": "reverse",
    "triplet_id": "745e4b78",
    "noun_class": "31",
    "id": 8146
  },
  {
    "video": "P28_06_103.mp4",
    "answer_text": "put-down",
    "direction": "reverse",
    "triplet_id": "745e4b78",
    "noun_class": "31",
    "id": 8147
  },
  {
    "video": "P30_111_426.mp4",
    "answer_text": "put-down",
    "direction": "reverse",
    "triplet_id": "745e4b78",
    "noun_class": "31",
    "id": 8148
  },
  {
    "video": "P30_111_76.mp4",
    "answer_text": "put-down",
    "direction": "reverse",
    "triplet_id": "745e4b78",
    "noun_class": "31",
    "id": 8149
  },
  {
    "video": "P12_101_39.mp4",
    "answer_text": "put-down",
    "direction": "reverse",
    "triplet_id": "745e4b78",
    "noun_class": "31",
    "id": 8150
  },
  {
    "video": "P22_111_342.mp4",
    "answer_text": "put-down",
    "direction": "reverse",
    "triplet_id": "745e4b78",
    "noun_class": "31",
    "id": 8151
  }
]