[
  {
    "video": "P01_09_190.mp4",
    "answer_text": "turn-on",
    "direction": "forward",
    "triplet_id": "21112a6a",
    "noun_class": "46",
    "id": 4145
  },
  {
    "video": "P26_105_93.mp4",
    "answer_text": "turn-on",
    "direction": "forward",
    "triplet_id": "21112a6a",
    "noun_class": "46",
    "id": 4146
  },
  {
    "video": "P06_101_280.mp4",
    "answer_text": "turn-on",
    "direction": "forward",
    "triplet_id": "21112a6a",
    "noun_class": "46",
    "id": 4147
  },
  {
    "video": "P02_120_219.mp4",
    "answer_text": "turn-on",
    "direction": "forward",
    "triplet_id": "21112a6a",
    "noun_class": "46",
    "id": 4148
  },
  {
    "video": "P06_05_151.mp4",
    "answer_text": "turn-on",
    "direction": "forward",
    "triplet_id": "21112a6a",
    "noun_class": "46",
    "id": 4149
  },
  {
    "video": "P13_09_10.mp4",
    "answer_text": "turn-on",
    "direction": "forward",
    "triplet_id": "21112a6a",
    "noun_class": "46",
    "id": 4150
  },
  {
    "video": "P04_110_20.mp4",
    "answer_text": "turn-on",
    "direction": "forward",
    "triplet_id": "21112a6a",
    "noun_class": "46",
    "id": 4151
  },
  {
    "video": "P04_113_0.mp4",
    "answer_text": "turn-on",
    "direction": "forward",
    "triplet_id": "21112a6a",
    "noun_class": "46",
    "id": 4152
  },
  {
    "video": "P16_01_4.mp4",
    "answer_text": "turn-on",
    "direction": "forward",
    "triplet_id": "21112a6a",
    "noun_class": "46",
    "id": 4153
  },
  {
    "video": "P26_104_12.mp4",
    "answer_text": "turn-on",
    "direction": "forward",
    "triplet_id": "21112a6a",
    "noun_class": "46",
    "id": 4154
  },
  {
    "video": "P30_111_250.mp4",
    "answer_text": "turn-on",
    "direction": "forward",
    "triplet_id": "21112a6a",
    "noun_class": "46",
    "id": 4155
  },
  {
    "video": "P11_15_19.mp4",
    "answer_text": "turn-on",
    "direction": "forward",
    "triplet_id": "21112a6a",
    "noun_class": "46",
    "id": 4156
  },
  {
    "video": "P13_08_67.mp4",
    "answer_text": "turn-on",
    "direction": "forward",
    "triplet_id": "21112a6a",
    "noun_class": "46",
    "id": 4157
  },
  {
    "video": "P26_115_7.mp4",
    "answer_text": "turn-on",
    "direction": "forward",
    "triplet_id": "21112a6a",
    "noun_class": "46",
    "id": 4158
  },
  {
    "video": "P07_101_29.mp4",
    "answer_text": "turn-on",
    "direction": "forward",
    "triplet_id": "21112a6a",
    "noun_class": "46",
    "id": 4159
  },
  {
    "video": "P02_112_259.mp4",
    "answer_text": "turn-on",
    "direction": "forward",
    "triplet_id": "21112a6a",
    "noun_class": "46",
    "id": 4160
  },
  {
    "video": "P26_04_11.mp4",
    "answer_text": "turn-on",
    "direction": "forward",
    "triplet_id": "21112a6a",
    "noun_class": "46",
    "id": 4161
  },
  {
    "video": "P24_08_59.mp4",
    "answer_text": "turn-on",
    "direction": "forward",
    "triplet_id": "21112a6a",
    "noun_class": "46",
    "id": 4162
  },
  {
    "video": "P35_103_220.mp4",
    "answer_text": "turn-on",
    "direction": "forward",
    "triplet_id": "21112a6a",
    "noun_class": "46",
    "id": 4163
  },
  {
    "video": "P28_106_4.mp4",
    "answer_text": "turn-on",
    "direction": "forward",
    "triplet_id": "21112a6a",
    "noun_class": "46",
    "id": 4164
  },
  {
    "video": "P06_108_5.mp4",
    "answer_text": "turn-on",
    "direction": "forward",
    "triplet_id": "21112a6a",
    "noun_class": "46",
    "id": 4165
  },
  {
    "video": "P22_16_303.mp4",
    "answer_text": "turn-on",
    "direction": "forward",
    "triplet_id": "21112a6a",
    "noun_class": "46",
    "id": 4166
  },
  {
    "video": "P26_119_0.mp4",
    "answer_text": "turn-on",
    "direction": "forward",
    "triplet_id": "21112a6a",
    "noun_class": "46",
    "id": 4167
  },
  {
    "video": "P15_02_28.mp4",
    "answer_text": "turn-on",
    "direction": "forward",
    "triplet_id": "21112a6a",
    "noun_class": "46",
    "id": 4168
  },
  {
    "video": "P03_119_6.mp4",
    "answer_text": "turn-on",
    "direction": "forward",
    "triplet_id": "21112a6a",
    "noun_class": "46",
    "id": 4169
  },
  {
    "video": "P11_105_4.mp4",
    "answer_text": "turn-on",
    "direction": "forward",
    "triplet_id": "21112a6a",
    "noun_class": "46",
    "id": 4170
  },
  {
    "video": "P03_122_4.mp4",
    "answer_text": "turn-on",
    "direction": "forward",
    "triplet_id": "21112a6a",
    "noun_class": "46",
    "id": 4171
  },
  {
    "video": "P28_10_0.mp4",
    "answer_text": "turn-on",
    "direction": "forward",
    "triplet_id": "21112a6a",
    "noun_class": "46",
    "id": 4172
  },
  {
    "video": "P11_05_2.mp4",
    "answer_text": "turn-on",
    "direction": "forward",
    "triplet_id": "21112a6a",
    "noun_class": "46",
    "id": 4173
  },
  {
    "video": "P11_103_0.mp4",
    "answer_text": "turn-on",
    "direction": "forward",
    "triplet_id": "21112a6a",
    "noun_class": "46",
    "id": 4174
  },
  {
    "video": "P13_08_158.mp4",
    "answer_text": "turn-off",
    "direction": "reverse",
    "triplet_id": "21112a6a",
    "noun_class": "46",
    "id": 4175
  },
  {
    "video": "P12_06_3.mp4",
    "answer_text": "turn-off",
    "direction": "reverse",
    "triplet_id": "21112a6a",
    "noun_class": "46",
    "id": 4176
  },
  {
    "video": "P07_103_13.mp4",
    "answer_text": "turn-off",
    "direction": "reverse",
    "triplet_id": "21112a6a",
    "noun_class": "46",
    "id": 4177
  },
  {
    "video": "P07_103_12.mp4",
    "answer_text": "turn-off",
    "direction": "reverse",
    "triplet_id": "21112a6a",
    "noun_class": "46",
    "id": 4178
  },
  {
    "video": "P11_104_0.mp4",
    "answer_text": "turn-off",
    "direction": "reverse",
    "triplet_id": "21112a6a",
    "noun_class": "46",
    "id": 4179
  },
  {
    "video": "P06_105_25.mp4",
    "answer_text": "turn-off",
    "direction": "reverse",
    "triplet_id": "21112a6a",
    "noun_class": "46",
    "id": 4180
  },
  {
    "video": "P04_109_418.mp4",
    "answer_text": "turn-off",
    "direction": "reverse",
    "triplet_id": "21112a6a",
    "noun_class": "46",
    "id": 4181
  },
  {
    "video": "P22_14_226.mp4",
    "answer_text": "turn-off",
    "direction": "reverse",
    "triplet_id": "21112a6a",
    "noun_class": "46",
    "id": 4182
  },
  {
    "video": "P24_05_277.mp4",
    "answer_text": "turn-off",
    "direction": "reverse",
    "triplet_id": "21112a6a",
    "noun_class": "46",
    "id": 4183
  },
  {
    "video": "P13_07_3.mp4",
    "answer_text": "turn-off",
    "direction": "reverse",
    "triplet_id": "21112a6a",
    "noun_class": "46",
    "id": 4184
  },
  {
    "video": "P22_08_365.mp4",
    "answer_text": "turn-off",
    "direction": "reverse",
    "triplet_id": "21112a6a",
    "noun_class": "46",
    "id": 4185
  },
  {
    "video": "P24_01_87.mp4",
    "answer_text": "turn-off",
    "direction": "reverse",
    "triplet_id": "21112a6a",
    "noun_class": "46",
    "id": 4186
  },
  {
    "video": "P12_05_2.mp4",
    "answer_text": "turn-off",
    "direction": "reverse",
    "triplet_id": "21112a6a",
    "noun_class": "46",
    "id": 4187
  },
  {
    "video": "P26_117_1.mp4",
    "answer_text": "turn-off",
    "direction": "reverse",
    "triplet_id": "21112a6a",
    "noun_class": "46",
    "id": 4188
  },
  {
    "video": "P22_07_735.mp4",
    "answer_text": "turn-off",
    "direction": "reverse",
    "triplet_id": "21112a6a",
    "noun_class": "46",
    "id": 4189
  },
  {
    "video": "P16_01_55.mp4",
    "answer_text": "turn-off",
    "direction": "reverse",
    "triplet_id": "21112a6a",
    "noun_class": "46",
    "id": 4190
  },
  {
    "video": "P03_120_138.mp4",
    "answer_text": "turn-off",
    "direction": "reverse",
    "triplet_id": "21112a6a",
    "noun_class": "46",
    "id": 4191
  },
  {
    "video": "P28_14_0.mp4",
    "answer_text": "turn-off",
    "direction": "reverse",
    "triplet_id": "21112a6a",
    "noun_class": "46",
    "id": 4192
  },
  {
    "video": "P04_116_95.mp4",
    "answer_text": "turn-off",
    "direction": "reverse",
    "triplet_id": "21112a6a",
    "noun_class": "46",
    "id": 4193
  },
  {
    "video": "P03_123_21.mp4",
    "answer_text": "turn-off",
    "direction": "reverse",
    "triplet_id": "21112a6a",
    "noun_class": "46",
    "id": 4194
  },
  {
    "video": "P14_02_5.mp4",
    "answer_text": "turn-off",
    "direction": "reverse",
    "triplet_id": "21112a6a",
    "noun_class": "46",
    "id": 4195
  },
  {
    "video": "P02_115_3.mp4",
    "answer_text": "turn-off",
    "direction": "reverse",
    "triplet_id": "21112a6a",
    "noun_class": "46",
    "id": 4196
  },
  {
    "video": "P22_07_638.mp4",
    "answer_text": "turn-off",
    "direction": "reverse",
    "triplet_id": "21112a6a",
    "noun_class": "46",
    "id": 4197
  },
  {
    "video": "P13_08_163.mp4",
    "answer_text": "turn-off",
    "direction": "reverse",
    "triplet_id": "21112a6a",
    "noun_class": "46",
    "id": 4198
  },
  {
    "video": "P06_110_4.mp4",
    "answer_text": "turn-off",
    "direction": "reverse",
    "triplet_id": "21112a6a",
    "noun_class": "46",
    "id": 4199
  },
  {
    "video": "P01_10_1.mp4",
    "answer_text": "turn-off",
    "direction": "reverse",
    "triplet_id": "21112a6a",
    "noun_class": "46",
    "id": 4200
  },
  {
    "video": "P30_112_2.mp4",
    "answer_text": "turn-off",
    "direction": "reverse",
    "triplet_id": "21112a6a",
    "noun_class": "46",
    "id": 4201
  }
]